aws_ecr_cleanup/__init__.py
aws_ecr_cleanup/configure_logging.py
aws_ecr_cleanup/main.py
aws_ecr_cleanup-0.1.5.dist-info/LICENSE
aws_ecr_cleanup-0.1.5.dist-info/METADATA
aws_ecr_cleanup-0.1.5.dist-info/WHEEL
aws_ecr_cleanup-0.1.5.dist-info/entry_points.txt
aws_ecr_cleanup-0.1.5.dist-info/top_level.txt
aws_ecr_cleanup-0.1.5.dist-info/RECORD
