Metadata-Version: 2.1
Name: aws-ecr-cleanup
Version: 0.1.5
Summary: A tool to remove stale images from AWS ECR repositories.
License: GNU GENERAL PUBLIC LICENSE
Project-URL: Homepage, https://github.com/thabiger/aws-ecr-cleanup
Classifier: Programming Language :: Python :: 3
Requires-Python: >=3.8
License-File: LICENSE
Requires-Dist: objectpath
Requires-Dist: boto3
Requires-Dist: jsonpath-ng
Requires-Dist: pyyaml
